Metadata-Version: 2.4
Name: orchard
Version: 2025.12.12
Summary: Python client for Orchard, a compute platform for Apple Silicon
Requires-Python: >=3.12
License-File: LICENSE
Requires-Dist: pillow
Requires-Dist: huggingface-hub
Requires-Dist: fastapi[standard]
Requires-Dist: pydantic-settings
Requires-Dist: jinja2
Requires-Dist: sse_starlette
Requires-Dist: filelock
Requires-Dist: pynng
Requires-Dist: requests
Provides-Extra: dev
Requires-Dist: pytest; extra == "dev"
Requires-Dist: pytest-asyncio; extra == "dev"
Requires-Dist: httpx; extra == "dev"
Requires-Dist: build; extra == "dev"
Requires-Dist: twine; extra == "dev"
Requires-Dist: ruff; extra == "dev"
Requires-Dist: pre-commit; extra == "dev"
Requires-Dist: ty>=0.0.1a29; extra == "dev"
Dynamic: license-file
